rokit_vai_package/__init__.py
rokit_vai_package/global_variable.py
rokit_vai_package/augment_mgmt/__init__.py
rokit_vai_package/augment_mgmt/augment_mgmt.py
rokit_vai_package/augment_mgmt/augmentation.py
rokit_vai_package/augment_mgmt/flip.py
rokit_vai_package/dataset_mgmt/__init__.py
rokit_vai_package/dataset_mgmt/aws_dataset_mgmt.py
rokit_vai_package/dataset_mgmt/dataset_mgmt.py
rokit_vai_package/dataset_mgmt/gcp_dataset_mgmt.py
rokit_vai_package/dataset_mgmt/storage_mgmt.py
rokit_vai_package/image_mgmt/__init__.py
rokit_vai_package/image_mgmt/image_mgmt.py
rokit_vai_package-0.0.0.14.dist-info/METADATA
rokit_vai_package-0.0.0.14.dist-info/WHEEL
rokit_vai_package-0.0.0.14.dist-info/top_level.txt
rokit_vai_package-0.0.0.14.dist-info/RECORD
